README.md
setup.py
ContextFreeGrammar/ContextFreeGrammar.c
ContextFreeGrammar/ContextFreeGrammar.pxd
ContextFreeGrammar/ContextFreeGrammar.pyx
ContextFreeGrammar/Rule.c
ContextFreeGrammar/Rule.pxd
ContextFreeGrammar/Rule.pyx
ContextFreeGrammar/RuleType.py
ContextFreeGrammar/__init__.py
ProbabilisticContextFreeGrammar/ProbabilisticContextFreeGrammar.c
ProbabilisticContextFreeGrammar/ProbabilisticContextFreeGrammar.pxd
ProbabilisticContextFreeGrammar/ProbabilisticContextFreeGrammar.pyx
ProbabilisticContextFreeGrammar/ProbabilisticParseNode.c
ProbabilisticContextFreeGrammar/ProbabilisticParseNode.pxd
ProbabilisticContextFreeGrammar/ProbabilisticParseNode.pyx
ProbabilisticContextFreeGrammar/ProbabilisticRule.c
ProbabilisticContextFreeGrammar/ProbabilisticRule.pxd
ProbabilisticContextFreeGrammar/ProbabilisticRule.pyx
ProbabilisticContextFreeGrammar/__init__.py
ProbabilisticParser/ProbabilisticCYKParser.c
ProbabilisticParser/ProbabilisticCYKParser.pxd
ProbabilisticParser/ProbabilisticCYKParser.pyx
ProbabilisticParser/__init__.py
SyntacticParser/CYKParser.c
SyntacticParser/CYKParser.pxd
SyntacticParser/CYKParser.pyx
SyntacticParser/PartialParseList.c
SyntacticParser/PartialParseList.pxd
SyntacticParser/PartialParseList.pyx
SyntacticParser/__init__.py
nlptoolkit_syntacticparser_cy.egg-info/PKG-INFO
nlptoolkit_syntacticparser_cy.egg-info/SOURCES.txt
nlptoolkit_syntacticparser_cy.egg-info/dependency_links.txt
nlptoolkit_syntacticparser_cy.egg-info/requires.txt
nlptoolkit_syntacticparser_cy.egg-info/top_level.txt